decontx/__init__.py
decontx/core.py
decontx/fast_ops.py
decontx/model.py
decontx/utils.py
decontx_python-0.2.0.dist-info/METADATA
decontx_python-0.2.0.dist-info/WHEEL
decontx_python-0.2.0.dist-info/RECORD
