Metadata-Version: 2.4
Name: decontx-python
Version: 0.2.0
Summary: Python implementation of DecontX for removing ambient RNA contamination from single-cell RNA-seq data
Project-URL: Homepage, https://github.com/NiRuff/decontx-python
Project-URL: Documentation, https://github.com/NiRuff/decontx-python
Project-URL: Repository, https://github.com/NiRuff/decontx-python
Project-URL: Bug Tracker, https://github.com/NiRuff/decontx-python/issues
Project-URL: Changelog, https://github.com/NiRuff/decontx-python/blob/main/CHANGELOG.md
Author-email: Nicolas Ruffini <nicolas.ruffini@posteo.de>
Maintainer-email: Nicolas Ruffini <nicolas.ruffini@posteo.de>
License-Expression: MIT
Keywords: RNA-seq,ambient-RNA,bayesian,bioinformatics,decontamination,scanpy,single-cell
Classifier: Development Status :: 4 - Beta
Classifier: Intended Audience :: Science/Research
Classifier: License :: OSI Approved :: MIT License
Classifier: Operating System :: OS Independent
Classifier: Programming Language :: Python :: 3
Classifier: Programming Language :: Python :: 3.8
Classifier: Programming Language :: Python :: 3.9
Classifier: Programming Language :: Python :: 3.10
Classifier: Programming Language :: Python :: 3.11
Classifier: Programming Language :: Python :: 3.12
Classifier: Topic :: Scientific/Engineering :: Bio-Informatics
Classifier: Topic :: Scientific/Engineering :: Medical Science Apps.
Requires-Python: >=3.8
Requires-Dist: anndata>=0.8.0
Requires-Dist: numba>=0.55.0
Requires-Dist: numpy>=1.21.0
Requires-Dist: pandas>=1.3.0
Requires-Dist: scanpy>=1.8.0
Requires-Dist: scikit-learn>=1.0.0
Requires-Dist: scipy>=1.7.0
Requires-Dist: tqdm>=4.60.0
Provides-Extra: all
Requires-Dist: black>=22.0; extra == 'all'
Requires-Dist: matplotlib>=3.5.0; extra == 'all'
Requires-Dist: mypy>=0.991; extra == 'all'
Requires-Dist: myst-parser>=0.18; extra == 'all'
Requires-Dist: pre-commit>=2.20; extra == 'all'
Requires-Dist: pytest-cov>=3.0; extra == 'all'
Requires-Dist: pytest>=6.0; extra == 'all'
Requires-Dist: ruff>=0.1.0; extra == 'all'
Requires-Dist: seaborn>=0.11.0; extra == 'all'
Requires-Dist: sphinx-rtd-theme>=1.0; extra == 'all'
Requires-Dist: sphinx>=4.0; extra == 'all'
Provides-Extra: dev
Requires-Dist: black>=22.0; extra == 'dev'
Requires-Dist: mypy>=0.991; extra == 'dev'
Requires-Dist: pre-commit>=2.20; extra == 'dev'
Requires-Dist: pytest-cov>=3.0; extra == 'dev'
Requires-Dist: pytest>=6.0; extra == 'dev'
Requires-Dist: ruff>=0.1.0; extra == 'dev'
Provides-Extra: docs
Requires-Dist: myst-parser>=0.18; extra == 'docs'
Requires-Dist: sphinx-rtd-theme>=1.0; extra == 'docs'
Requires-Dist: sphinx>=4.0; extra == 'docs'
Provides-Extra: plotting
Requires-Dist: matplotlib>=3.5.0; extra == 'plotting'
Requires-Dist: seaborn>=0.11.0; extra == 'plotting'
Provides-Extra: test
Requires-Dist: pytest-cov>=3.0; extra == 'test'
Requires-Dist: pytest>=6.0; extra == 'test'
